setversion.py
setversion-1.0.1.dist-info/licenses/LICENSE
setversion-1.0.1.dist-info/METADATA
setversion-1.0.1.dist-info/WHEEL
setversion-1.0.1.dist-info/entry_points.txt
setversion-1.0.1.dist-info/top_level.txt
setversion-1.0.1.dist-info/RECORD
