Metadata-Version: 2.4
Name: setversion
Version: 1.0.1
Summary: Quickly change the version of stack by adjusting the compose file
Author-email: Nathan Shearer <shearern@gmail.com>
License-Expression: MIT AND (Apache-2.0 OR BSD-2-Clause)
Project-URL: Repository, https://gitlab.com/shearern/setversion
Requires-Python: >=3.7
License-File: LICENSE
Dynamic: license-file
